{"candlesticks": [{"end_period_ts": 1780542000, "open_interest_fp": "11.00", "price": {"close_dollars": "0.3000", "high_dollars": "0.3100", "low_dollars": "0.3000", "mean_dollars": "0.3073", "open_dollars": "0.3100"}, "volume_fp": "11.00", "yes_ask": {"close_dollars": "0.3100", "high_dollars": "1.0000", "low_dollars": "0.3000", "open_dollars": "1.0000"}, "yes_bid": {"close_dollars": "0.2600", "high_dollars": "0.2600", "low_dollars": "0.0100", "open_dollars": "0.0100"}}, {"end_period_ts": 1780545600, "open_interest_fp": "11.00", "price": {"previous_dollars": "0.3000"}, "volume_fp": "0.00", "yes_ask": {"close_dollars": "0.3100", "high_dollars": "0.3100", "low_dollars": "0.3100", "open_dollars": "0.3100"}, "yes_bid": {"close_dollars": "0.3000", "high_dollars": "0.3000", "low_dollars": "0.2300", "open_dollars": "0.2600"}}, {"end_period_ts": 1780549200, "open_interest_fp": "162.18", "price": {"close_dollars": "0.3100", "high_dollars": "0.3100", "low_dollars": "0.3000", "mean_dollars": "0.3097", "open_dollars": "0.3000", "previous_dollars": "0.3000"}, "volume_fp": "151.18", "yes_ask": {"close_dollars": "0.3100", "high_dollars": "0.3100", "low_dollars": "0.3100", "open_dollars": "0.3100"}, "yes_bid": {"close_dollars": "0.3000", "high_dollars": "0.3000", "low_dollars": "0.3000", "open_dollars": "0.3000"}}, {"end_period_ts": 1780552800, "open_interest_fp": "162.18", "price": {"previous_dollars": "0.3100"}, "volume_fp": "0.00", "yes_ask": {"close_dollars": "0.3100", "high_dollars": "0.3100", "low_dollars": "0.3100", "open_dollars": "0.3100"}, "yes_bid": {"close_dollars": "0.3000", "high_dollars": "0.3000", "low_dollars": "0.3000", "open_dollars": "0.3000"}}, {"end_period_ts": 1780556400, "open_interest_fp": "163.18", "price": {"close_dollars": "0.3100", "high_dollars": "0.3100", "low_dollars": "0.3100", "mean_dollars": "0.3100", "open_dollars": "0.3100", "previous_dollars": "0.3100"}, "volume_fp": "1.00", "yes_ask": {"close_dollars": "0.3100", "high_dollars": "0.3100", "low_dollars": "0.3100", "open_dollars": "0.3100"}, "yes_bid": {"close_dollars": "0.3000", "high_dollars": "0.3000", "low_dollars": "0.3000", "open_dollars": "0.3000"}}, {"end_period_ts": 1780567200, "open_interest_fp": "163.18", "price": {"previous_dollars": "0.3100"}, "volume_fp": "0.00", "yes_ask": {"close_dollars": "0.3100", "high_dollars": "0.3100", "low_dollars": "0.3100", "open_dollars": "0.3100"}, "yes_bid": {"close_dollars": "0.3000", "high_dollars": "0.3000", "low_dollars": "0.3000", "open_dollars": "0.3000"}}, {"end_period_ts": 1780570800, "open_interest_fp": "164.54", "price": {"close_dollars": "0.3000", "high_dollars": "0.3000", "low_dollars": "0.3000", "mean_dollars": "0.3000", "open_dollars": "0.3000", "previous_dollars": "0.3100"}, "volume_fp": "1.36", "yes_ask": {"close_dollars": "0.3100", "high_dollars": "0.3100", "low_dollars": "0.3100", "open_dollars": "0.3100"}, "yes_bid": {"close_dollars": "0.3000", "high_dollars": "0.3000", "low_dollars": "0.3000", "open_dollars": "0.3000"}}, {"end_period_ts": 1780574400, "open_interest_fp": "170.54", "price": {"close_dollars": "0.3000", "high_dollars": "0.3000", "low_dollars": "0.3000", "mean_dollars": "0.3000", "open_dollars": "0.3000", "previous_dollars": "0.3000"}, "volume_fp": "6.00", "yes_ask": {"close_dollars": "0.3100", "high_dollars": "0.3100", "low_dollars": "0.3100", "open_dollars": "0.3100"}, "yes_bid": {"close_dollars": "0.3000", "high_dollars": "0.3000", "low_dollars": "0.3000", "open_dollars": "0.3000"}}, {"end_period_ts": 1780578000, "open_interest_fp": "171.22", "price": {"close_dollars": "0.3000", "high_dollars": "0.3000", "low_dollars": "0.3000", "mean_dollars": "0.3000", "open_dollars": "0.3000", "previous_dollars": "0.3000"}, "volume_fp": "0.68", "yes_ask": {"close_dollars": "0.3100", "high_dollars": "0.3100", "low_dollars": "0.3100", "open_dollars": "0.3100"}, "yes_bid": {"close_dollars": "0.3000", "high_dollars": "0.3000", "low_dollars": "0.3000", "open_dollars": "0.3000"}}, {"end_period_ts": 1780581600, "open_interest_fp": "171.22", "price": {"previous_dollars": "0.3000"}, "volume_fp": "0.00", "yes_ask": {"close_dollars": "0.3100", "high_dollars": "0.3100", "low_dollars": "0.3100", "open_dollars": "0.3100"}, "yes_bid": {"close_dollars": "0.3000", "high_dollars": "0.3000", "low_dollars": "0.3000", "open_dollars": "0.3000"}}, {"end_period_ts": 1780585200, "open_interest_fp": "171.22", "price": {"previous_dollars": "0.3000"}, "volume_fp": "0.00", "yes_ask": {"close_dollars": "0.3100", "high_dollars": "0.3100", "low_dollars": "0.3100", "open_dollars": "0.3100"}, "yes_bid": {"close_dollars": "0.3000", "high_dollars": "0.3000", "low_dollars": "0.3000", "open_dollars": "0.3000"}}, {"end_period_ts": 1780588800, "open_interest_fp": "171.22", "price": {"previous_dollars": "0.3000"}, "volume_fp": "0.00", "yes_ask": {"close_dollars": "0.3100", "high_dollars": "0.3100", "low_dollars": "0.3100", "open_dollars": "0.3100"}, "yes_bid": {"close_dollars": "0.3000", "high_dollars": "0.3000", "low_dollars": "0.3000", "open_dollars": "0.3000"}}, {"end_period_ts": 1780592400, "open_interest_fp": "186.60", "price": {"close_dollars": "0.3100", "high_dollars": "0.3100", "low_dollars": "0.3100", "mean_dollars": "0.3100", "open_dollars": "0.3100", "previous_dollars": "0.3000"}, "volume_fp": "15.38", "yes_ask": {"close_dollars": "0.3100", "high_dollars": "0.3100", "low_dollars": "0.3100", "open_dollars": "0.3100"}, "yes_bid": {"close_dollars": "0.3000", "high_dollars": "0.3000", "low_dollars": "0.3000", "open_dollars": "0.3000"}}, {"end_period_ts": 1780599600, "open_interest_fp": "194.56", "price": {"close_dollars": "0.3000", "high_dollars": "0.3000", "low_dollars": "0.3000", "mean_dollars": "0.3000", "open_dollars": "0.3000", "previous_dollars": "0.3100"}, "volume_fp": "7.96", "yes_ask": {"close_dollars": "0.3100", "high_dollars": "0.3100", "low_dollars": "0.3100", "open_dollars": "0.3100"}, "yes_bid": {"close_dollars": "0.3000", "high_dollars": "0.3000", "low_dollars": "0.3000", "open_dollars": "0.3000"}}, {"end_period_ts": 1780603200, "open_interest_fp": "209.68", "price": {"close_dollars": "0.3100", "high_dollars": "0.3100", "low_dollars": "0.3100", "mean_dollars": "0.3100", "open_dollars": "0.3100", "previous_dollars": "0.3000"}, "volume_fp": "15.12", "yes_ask": {"close_dollars": "0.3100", "high_dollars": "0.3100", "low_dollars": "0.3100", "open_dollars": "0.3100"}, "yes_bid": {"close_dollars": "0.3000", "high_dollars": "0.3000", "low_dollars": "0.3000", "open_dollars": "0.3000"}}, {"end_period_ts": 1780606800, "open_interest_fp": "212.75", "price": {"close_dollars": "0.3100", "high_dollars": "0.3100", "low_dollars": "0.3100", "mean_dollars": "0.3100", "open_dollars": "0.3100", "previous_dollars": "0.3100"}, "volume_fp": "3.07", "yes_ask": {"close_dollars": "0.3100", "high_dollars": "0.3100", "low_dollars": "0.3100", "open_dollars": "0.3100"}, "yes_bid": {"close_dollars": "0.3000", "high_dollars": "0.3000", "low_dollars": "0.3000", "open_dollars": "0.3000"}}, {"end_period_ts": 1780610400, "open_interest_fp": "221.75", "price": {"close_dollars": "0.3100", "high_dollars": "0.3100", "low_dollars": "0.3100", "mean_dollars": "0.3100", "open_dollars": "0.3100", "previous_dollars": "0.3100"}, "volume_fp": "9.00", "yes_ask": {"close_dollars": "0.3100", "high_dollars": "0.3100", "low_dollars": "0.3100", "open_dollars": "0.3100"}, "yes_bid": {"close_dollars": "0.3000", "high_dollars": "0.3000", "low_dollars": "0.3000", "open_dollars": "0.3000"}}, {"end_period_ts": 1780614000, "open_interest_fp": "221.75", "price": {"previous_dollars": "0.3100"}, "volume_fp": "0.00", "yes_ask": {"close_dollars": "0.3100", "high_dollars": "0.3100", "low_dollars": "0.3100", "open_dollars": "0.3100"}, "yes_bid": {"close_dollars": "0.3000", "high_dollars": "0.3000", "low_dollars": "0.3000", "open_dollars": "0.3000"}}, {"end_period_ts": 1780621200, "open_interest_fp": "221.75", "price": {"previous_dollars": "0.3100"}, "volume_fp": "0.00", "yes_ask": {"close_dollars": "0.3100", "high_dollars": "0.3100", "low_dollars": "0.3100", "open_dollars": "0.3100"}, "yes_bid": {"close_dollars": "0.3000", "high_dollars": "0.3000", "low_dollars": "0.3000", "open_dollars": "0.3000"}}, {"end_period_ts": 1780624800, "open_interest_fp": "237.75", "price": {"close_dollars": "0.3100", "high_dollars": "0.3100", "low_dollars": "0.3100", "mean_dollars": "0.3100", "open_dollars": "0.3100", "previous_dollars": "0.3100"}, "volume_fp": "16.00", "yes_ask": {"close_dollars": "0.3100", "high_dollars": "0.3100", "low_dollars": "0.3100", "open_dollars": "0.3100"}, "yes_bid": {"close_dollars": "0.3000", "high_dollars": "0.3000", "low_dollars": "0.3000", "open_dollars": "0.3000"}}, {"end_period_ts": 1780628400, "open_interest_fp": "244.75", "price": {"close_dollars": "0.3100", "high_dollars": "0.3100", "low_dollars": "0.3100", "mean_dollars": "0.3100", "open_dollars": "0.3100", "previous_dollars": "0.3100"}, "volume_fp": "7.00", "yes_ask": {"close_dollars": "0.3100", "high_dollars": "0.3100", "low_dollars": "0.3100", "open_dollars": "0.3100"}, "yes_bid": {"close_dollars": "0.3000", "high_dollars": "0.3000", "low_dollars": "0.3000", "open_dollars": "0.3000"}}, {"end_period_ts": 1780632000, "open_interest_fp": "260.75", "price": {"close_dollars": "0.3000", "high_dollars": "0.3000", "low_dollars": "0.3000", "mean_dollars": "0.3000", "open_dollars": "0.3000", "previous_dollars": "0.3100"}, "volume_fp": "16.00", "yes_ask": {"close_dollars": "0.3100", "high_dollars": "0.3100", "low_dollars": "0.3100", "open_dollars": "0.3100"}, "yes_bid": {"close_dollars": "0.3000", "high_dollars": "0.3000", "low_dollars": "0.3000", "open_dollars": "0.3000"}}, {"end_period_ts": 1780635600, "open_interest_fp": "291.75", "price": {"close_dollars": "0.3000", "high_dollars": "0.3100", "low_dollars": "0.3000", "mean_dollars": "0.3003", "open_dollars": "0.3000", "previous_dollars": "0.3000"}, "volume_fp": "31.00", "yes_ask": {"close_dollars": "0.3000", "high_dollars": "0.3100", "low_dollars": "0.3000", "open_dollars": "0.3100"}, "yes_bid": {"close_dollars": "0.2700", "high_dollars": "0.3000", "low_dollars": "0.2600", "open_dollars": "0.3000"}}, {"end_period_ts": 1780639200, "open_interest_fp": "298.75", "price": {"close_dollars": "0.2700", "high_dollars": "0.3000", "low_dollars": "0.2700", "mean_dollars": "0.2910", "open_dollars": "0.3000", "previous_dollars": "0.3000"}, "volume_fp": "10.00", "yes_ask": {"close_dollars": "0.2900", "high_dollars": "0.3000", "low_dollars": "0.2800", "open_dollars": "0.3000"}, "yes_bid": {"close_dollars": "0.2800", "high_dollars": "0.2800", "low_dollars": "0.2500", "open_dollars": "0.2700"}}, {"end_period_ts": 1780642800, "open_interest_fp": "340.75", "price": {"close_dollars": "0.3000", "high_dollars": "0.3000", "low_dollars": "0.3000", "mean_dollars": "0.3000", "open_dollars": "0.3000", "previous_dollars": "0.2700"}, "volume_fp": "45.00", "yes_ask": {"close_dollars": "0.3000", "high_dollars": "0.3100", "low_dollars": "0.2900", "open_dollars": "0.2900"}, "yes_bid": {"close_dollars": "0.2800", "high_dollars": "0.2800", "low_dollars": "0.2800", "open_dollars": "0.2800"}}, {"end_period_ts": 1780646400, "open_interest_fp": "340.75", "price": {"previous_dollars": "0.3000"}, "volume_fp": "0.00", "yes_ask": {"close_dollars": "0.3000", "high_dollars": "0.3000", "low_dollars": "0.3000", "open_dollars": "0.3000"}, "yes_bid": {"close_dollars": "0.2800", "high_dollars": "0.2800", "low_dollars": "0.2800", "open_dollars": "0.2800"}}, {"end_period_ts": 1780650000, "open_interest_fp": "373.52", "price": {"close_dollars": "0.3000", "high_dollars": "0.3000", "low_dollars": "0.3000", "mean_dollars": "0.3000", "open_dollars": "0.3000", "previous_dollars": "0.3000"}, "volume_fp": "32.77", "yes_ask": {"close_dollars": "0.3000", "high_dollars": "0.3000", "low_dollars": "0.2900", "open_dollars": "0.3000"}, "yes_bid": {"close_dollars": "0.2700", "high_dollars": "0.2800", "low_dollars": "0.2600", "open_dollars": "0.2800"}}, {"end_period_ts": 1780653600, "open_interest_fp": "373.52", "price": {"previous_dollars": "0.3000"}, "volume_fp": "0.00", "yes_ask": {"close_dollars": "0.3000", "high_dollars": "0.3000", "low_dollars": "0.2900", "open_dollars": "0.3000"}, "yes_bid": {"close_dollars": "0.2700", "high_dollars": "0.2700", "low_dollars": "0.2700", "open_dollars": "0.2700"}}, {"end_period_ts": 1780657200, "open_interest_fp": "373.52", "price": {"previous_dollars": "0.3000"}, "volume_fp": "0.00", "yes_ask": {"close_dollars": "0.2900", "high_dollars": "0.3000", "low_dollars": "0.2900", "open_dollars": "0.3000"}, "yes_bid": {"close_dollars": "0.2700", "high_dollars": "0.2700", "low_dollars": "0.2700", "open_dollars": "0.2700"}}, {"end_period_ts": 1780660800, "open_interest_fp": "379.52", "price": {"close_dollars": "0.2900", "high_dollars": "0.2900", "low_dollars": "0.2900", "mean_dollars": "0.2900", "open_dollars": "0.2900", "previous_dollars": "0.3000"}, "volume_fp": "6.00", "yes_ask": {"close_dollars": "0.2900", "high_dollars": "0.2900", "low_dollars": "0.2800", "open_dollars": "0.2900"}, "yes_bid": {"close_dollars": "0.2700", "high_dollars": "0.2700", "low_dollars": "0.2600", "open_dollars": "0.2700"}}, {"end_period_ts": 1780664400, "open_interest_fp": "381.19", "price": {"close_dollars": "0.2900", "high_dollars": "0.2900", "low_dollars": "0.2900", "mean_dollars": "0.2900", "open_dollars": "0.2900", "previous_dollars": "0.2900"}, "volume_fp": "1.67", "yes_ask": {"close_dollars": "0.2900", "high_dollars": "0.2900", "low_dollars": "0.2800", "open_dollars": "0.2900"}, "yes_bid": {"close_dollars": "0.2700", "high_dollars": "0.2700", "low_dollars": "0.2600", "open_dollars": "0.2700"}}, {"end_period_ts": 1780668000, "open_interest_fp": "383.19", "price": {"close_dollars": "0.2900", "high_dollars": "0.2900", "low_dollars": "0.2900", "mean_dollars": "0.2900", "open_dollars": "0.2900", "previous_dollars": "0.2900"}, "volume_fp": "2.00", "yes_ask": {"close_dollars": "0.2900", "high_dollars": "0.2900", "low_dollars": "0.2900", "open_dollars": "0.2900"}, "yes_bid": {"close_dollars": "0.2700", "high_dollars": "0.2700", "low_dollars": "0.2700", "open_dollars": "0.2700"}}, {"end_period_ts": 1780671600, "open_interest_fp": "383.19", "price": {"previous_dollars": "0.2900"}, "volume_fp": "0.00", "yes_ask": {"close_dollars": "0.2900", "high_dollars": "0.2900", "low_dollars": "0.2900", "open_dollars": "0.2900"}, "yes_bid": {"close_dollars": "0.2700", "high_dollars": "0.2700", "low_dollars": "0.2600", "open_dollars": "0.2700"}}, {"end_period_ts": 1780675200, "open_interest_fp": "621.19", "price": {"close_dollars": "0.2900", "high_dollars": "0.2900", "low_dollars": "0.2900", "mean_dollars": "0.2900", "open_dollars": "0.2900", "previous_dollars": "0.2900"}, "volume_fp": "238.00", "yes_ask": {"close_dollars": "0.2900", "high_dollars": "0.3000", "low_dollars": "0.2900", "open_dollars": "0.2900"}, "yes_bid": {"close_dollars": "0.2700", "high_dollars": "0.2700", "low_dollars": "0.2700", "open_dollars": "0.2700"}}, {"end_period_ts": 1780678800, "open_interest_fp": "654.19", "price": {"close_dollars": "0.2900", "high_dollars": "0.2900", "low_dollars": "0.2900", "mean_dollars": "0.2900", "open_dollars": "0.2900", "previous_dollars": "0.2900"}, "volume_fp": "33.00", "yes_ask": {"close_dollars": "0.2900", "high_dollars": "0.2900", "low_dollars": "0.2900", "open_dollars": "0.2900"}, "yes_bid": {"close_dollars": "0.2700", "high_dollars": "0.2700", "low_dollars": "0.2700", "open_dollars": "0.2700"}}, {"end_period_ts": 1780682400, "open_interest_fp": "1237.45", "price": {"close_dollars": "0.3100", "high_dollars": "0.3100", "low_dollars": "0.2800", "mean_dollars": "0.2944", "open_dollars": "0.2900", "previous_dollars": "0.2900"}, "volume_fp": "583.26", "yes_ask": {"close_dollars": "0.2900", "high_dollars": "0.3100", "low_dollars": "0.2800", "open_dollars": "0.2900"}, "yes_bid": {"close_dollars": "0.2700", "high_dollars": "0.2700", "low_dollars": "0.2700", "open_dollars": "0.2700"}}, {"end_period_ts": 1780686000, "open_interest_fp": "1281.68", "price": {"close_dollars": "0.2700", "high_dollars": "0.2700", "low_dollars": "0.2700", "mean_dollars": "0.2700", "open_dollars": "0.2700", "previous_dollars": "0.3100"}, "volume_fp": "200.00", "yes_ask": {"close_dollars": "0.2700", "high_dollars": "0.2900", "low_dollars": "0.2700", "open_dollars": "0.2900"}, "yes_bid": {"close_dollars": "0.2600", "high_dollars": "0.2700", "low_dollars": "0.2600", "open_dollars": "0.2700"}}, {"end_period_ts": 1780689600, "open_interest_fp": "1284.68", "price": {"close_dollars": "0.2700", "high_dollars": "0.2700", "low_dollars": "0.2700", "mean_dollars": "0.2700", "open_dollars": "0.2700", "previous_dollars": "0.2700"}, "volume_fp": "3.00", "yes_ask": {"close_dollars": "0.2700", "high_dollars": "0.2700", "low_dollars": "0.2700", "open_dollars": "0.2700"}, "yes_bid": {"close_dollars": "0.2600", "high_dollars": "0.2600", "low_dollars": "0.2500", "open_dollars": "0.2600"}}, {"end_period_ts": 1780693200, "open_interest_fp": "1978.20", "price": {"close_dollars": "0.2700", "high_dollars": "0.2700", "low_dollars": "0.2600", "mean_dollars": "0.2695", "open_dollars": "0.2700", "previous_dollars": "0.2700"}, "volume_fp": "727.52", "yes_ask": {"close_dollars": "0.2700", "high_dollars": "0.2700", "low_dollars": "0.2700", "open_dollars": "0.2700"}, "yes_bid": {"close_dollars": "0.2600", "high_dollars": "0.2600", "low_dollars": "0.2600", "open_dollars": "0.2600"}}, {"end_period_ts": 1780696800, "open_interest_fp": "2238.20", "price": {"close_dollars": "0.2600", "high_dollars": "0.2600", "low_dollars": "0.2600", "mean_dollars": "0.2600", "open_dollars": "0.2600", "previous_dollars": "0.2700"}, "volume_fp": "670.00", "yes_ask": {"close_dollars": "0.2600", "high_dollars": "0.2700", "low_dollars": "0.2600", "open_dollars": "0.2700"}, "yes_bid": {"close_dollars": "0.2500", "high_dollars": "0.2600", "low_dollars": "0.2500", "open_dollars": "0.2600"}}, {"end_period_ts": 1780700400, "open_interest_fp": "2263.14", "price": {"close_dollars": "0.2600", "high_dollars": "0.2600", "low_dollars": "0.2600", "mean_dollars": "0.2600", "open_dollars": "0.2600", "previous_dollars": "0.2600"}, "volume_fp": "24.94", "yes_ask": {"close_dollars": "0.2600", "high_dollars": "0.2600", "low_dollars": "0.2600", "open_dollars": "0.2600"}, "yes_bid": {"close_dollars": "0.2500", "high_dollars": "0.2500", "low_dollars": "0.2500", "open_dollars": "0.2500"}}, {"end_period_ts": 1780704000, "open_interest_fp": "2881.76", "price": {"close_dollars": "0.2600", "high_dollars": "0.2600", "low_dollars": "0.2600", "mean_dollars": "0.2600", "open_dollars": "0.2600", "previous_dollars": "0.2600"}, "volume_fp": "618.62", "yes_ask": {"close_dollars": "0.2600", "high_dollars": "0.2600", "low_dollars": "0.2600", "open_dollars": "0.2600"}, "yes_bid": {"close_dollars": "0.2500", "high_dollars": "0.2500", "low_dollars": "0.2500", "open_dollars": "0.2500"}}, {"end_period_ts": 1780707600, "open_interest_fp": "2897.76", "price": {"close_dollars": "0.2700", "high_dollars": "0.2700", "low_dollars": "0.2700", "mean_dollars": "0.2700", "open_dollars": "0.2700", "previous_dollars": "0.2600"}, "volume_fp": "16.00", "yes_ask": {"close_dollars": "0.2700", "high_dollars": "0.2700", "low_dollars": "0.2600", "open_dollars": "0.2600"}, "yes_bid": {"close_dollars": "0.2600", "high_dollars": "0.2600", "low_dollars": "0.2500", "open_dollars": "0.2500"}}, {"end_period_ts": 1780711200, "open_interest_fp": "3151.32", "price": {"close_dollars": "0.2600", "high_dollars": "0.2600", "low_dollars": "0.2600", "mean_dollars": "0.2600", "open_dollars": "0.2600", "previous_dollars": "0.2700"}, "volume_fp": "253.56", "yes_ask": {"close_dollars": "0.2600", "high_dollars": "0.2700", "low_dollars": "0.2600", "open_dollars": "0.2700"}, "yes_bid": {"close_dollars": "0.2500", "high_dollars": "0.2600", "low_dollars": "0.2500", "open_dollars": "0.2600"}}, {"end_period_ts": 1780714800, "open_interest_fp": "6202.63", "price": {"close_dollars": "0.2600", "high_dollars": "0.2600", "low_dollars": "0.2400", "mean_dollars": "0.2564", "open_dollars": "0.2600", "previous_dollars": "0.2600"}, "volume_fp": "3599.82", "yes_ask": {"close_dollars": "0.2600", "high_dollars": "0.2600", "low_dollars": "0.2500", "open_dollars": "0.2600"}, "yes_bid": {"close_dollars": "0.2400", "high_dollars": "0.2500", "low_dollars": "0.2400", "open_dollars": "0.2500"}}, {"end_period_ts": 1780718400, "open_interest_fp": "22657.79", "price": {"close_dollars": "0.2600", "high_dollars": "0.2600", "low_dollars": "0.2500", "mean_dollars": "0.2600", "open_dollars": "0.2600", "previous_dollars": "0.2600"}, "volume_fp": "16875.84", "yes_ask": {"close_dollars": "0.2600", "high_dollars": "0.2600", "low_dollars": "0.2600", "open_dollars": "0.2600"}, "yes_bid": {"close_dollars": "0.2500", "high_dollars": "0.2500", "low_dollars": "0.2400", "open_dollars": "0.2400"}}, {"end_period_ts": 1780722000, "open_interest_fp": "40403.30", "price": {"close_dollars": "0.2600", "high_dollars": "0.2600", "low_dollars": "0.2400", "mean_dollars": "0.2510", "open_dollars": "0.2600", "previous_dollars": "0.2600"}, "volume_fp": "33137.85", "yes_ask": {"close_dollars": "0.2600", "high_dollars": "0.2600", "low_dollars": "0.2600", "open_dollars": "0.2600"}, "yes_bid": {"close_dollars": "0.2400", "high_dollars": "0.2500", "low_dollars": "0.2400", "open_dollars": "0.2500"}}, {"end_period_ts": 1780725600, "open_interest_fp": "40090.75", "price": {"close_dollars": "0.2600", "high_dollars": "0.2600", "low_dollars": "0.2400", "mean_dollars": "0.2446", "open_dollars": "0.2600", "previous_dollars": "0.2600"}, "volume_fp": "9715.67", "yes_ask": {"close_dollars": "0.2600", "high_dollars": "0.2600", "low_dollars": "0.2500", "open_dollars": "0.2600"}, "yes_bid": {"close_dollars": "0.2400", "high_dollars": "0.2500", "low_dollars": "0.2400", "open_dollars": "0.2400"}}, {"end_period_ts": 1780729200, "open_interest_fp": "41231.50", "price": {"close_dollars": "0.2600", "high_dollars": "0.2600", "low_dollars": "0.2400", "mean_dollars": "0.2587", "open_dollars": "0.2600", "previous_dollars": "0.2600"}, "volume_fp": "1314.01", "yes_ask": {"close_dollars": "0.2600", "high_dollars": "0.2600", "low_dollars": "0.2600", "open_dollars": "0.2600"}, "yes_bid": {"close_dollars": "0.2400", "high_dollars": "0.2500", "low_dollars": "0.2400", "open_dollars": "0.2400"}}, {"end_period_ts": 1780732800, "open_interest_fp": "41823.62", "price": {"close_dollars": "0.2500", "high_dollars": "0.2600", "low_dollars": "0.2400", "mean_dollars": "0.2516", "open_dollars": "0.2600", "previous_dollars": "0.2600"}, "volume_fp": "1323.46", "yes_ask": {"close_dollars": "0.2500", "high_dollars": "0.2600", "low_dollars": "0.2500", "open_dollars": "0.2600"}, "yes_bid": {"close_dollars": "0.2400", "high_dollars": "0.2400", "low_dollars": "0.2400", "open_dollars": "0.2400"}}, {"end_period_ts": 1780736400, "open_interest_fp": "42692.42", "price": {"close_dollars": "0.2500", "high_dollars": "0.2500", "low_dollars": "0.2400", "mean_dollars": "0.2497", "open_dollars": "0.2500", "previous_dollars": "0.2500"}, "volume_fp": "920.80", "yes_ask": {"close_dollars": "0.2500", "high_dollars": "0.2500", "low_dollars": "0.2500", "open_dollars": "0.2500"}, "yes_bid": {"close_dollars": "0.2400", "high_dollars": "0.2400", "low_dollars": "0.2400", "open_dollars": "0.2400"}}, {"end_period_ts": 1780740000, "open_interest_fp": "43057.11", "price": {"close_dollars": "0.2500", "high_dollars": "0.2600", "low_dollars": "0.2500", "mean_dollars": "0.2501", "open_dollars": "0.2500", "previous_dollars": "0.2500"}, "volume_fp": "364.69", "yes_ask": {"close_dollars": "0.2500", "high_dollars": "0.2600", "low_dollars": "0.2500", "open_dollars": "0.2500"}, "yes_bid": {"close_dollars": "0.2400", "high_dollars": "0.2500", "low_dollars": "0.2400", "open_dollars": "0.2400"}}, {"end_period_ts": 1780743600, "open_interest_fp": "44531.48", "price": {"close_dollars": "0.2600", "high_dollars": "0.2600", "low_dollars": "0.2500", "mean_dollars": "0.2527", "open_dollars": "0.2500", "previous_dollars": "0.2500"}, "volume_fp": "1652.37", "yes_ask": {"close_dollars": "0.2600", "high_dollars": "0.2600", "low_dollars": "0.2500", "open_dollars": "0.2500"}, "yes_bid": {"close_dollars": "0.2500", "high_dollars": "0.2500", "low_dollars": "0.2400", "open_dollars": "0.2400"}}, {"end_period_ts": 1780747200, "open_interest_fp": "45171.65", "price": {"close_dollars": "0.2500", "high_dollars": "0.2600", "low_dollars": "0.2500", "mean_dollars": "0.2538", "open_dollars": "0.2600", "previous_dollars": "0.2600"}, "volume_fp": "640.17", "yes_ask": {"close_dollars": "0.2500", "high_dollars": "0.2600", "low_dollars": "0.2500", "open_dollars": "0.2600"}, "yes_bid": {"close_dollars": "0.2400", "high_dollars": "0.2500", "low_dollars": "0.2400", "open_dollars": "0.2500"}}, {"end_period_ts": 1780750800, "open_interest_fp": "46058.85", "price": {"close_dollars": "0.2500", "high_dollars": "0.2500", "low_dollars": "0.2500", "mean_dollars": "0.2500", "open_dollars": "0.2500", "previous_dollars": "0.2500"}, "volume_fp": "887.20", "yes_ask": {"close_dollars": "0.2500", "high_dollars": "0.2500", "low_dollars": "0.2500", "open_dollars": "0.2500"}, "yes_bid": {"close_dollars": "0.2400", "high_dollars": "0.2400", "low_dollars": "0.2400", "open_dollars": "0.2400"}}, {"end_period_ts": 1780754400, "open_interest_fp": "55702.88", "price": {"close_dollars": "0.2400", "high_dollars": "0.2500", "low_dollars": "0.2300", "mean_dollars": "0.2489", "open_dollars": "0.2500", "previous_dollars": "0.2500"}, "volume_fp": "9719.03", "yes_ask": {"close_dollars": "0.2400", "high_dollars": "0.2500", "low_dollars": "0.2400", "open_dollars": "0.2500"}, "yes_bid": {"close_dollars": "0.2300", "high_dollars": "0.2400", "low_dollars": "0.2300", "open_dollars": "0.2400"}}, {"end_period_ts": 1780758000, "open_interest_fp": "67869.17", "price": {"close_dollars": "0.2500", "high_dollars": "0.2500", "low_dollars": "0.2300", "mean_dollars": "0.2426", "open_dollars": "0.2400", "previous_dollars": "0.2400"}, "volume_fp": "12678.13", "yes_ask": {"close_dollars": "0.2500", "high_dollars": "0.2500", "low_dollars": "0.2400", "open_dollars": "0.2400"}, "yes_bid": {"close_dollars": "0.2300", "high_dollars": "0.2400", "low_dollars": "0.2300", "open_dollars": "0.2300"}}, {"end_period_ts": 1780761600, "open_interest_fp": "74654.21", "price": {"close_dollars": "0.2500", "high_dollars": "0.2500", "low_dollars": "0.2300", "mean_dollars": "0.2483", "open_dollars": "0.2500", "previous_dollars": "0.2500"}, "volume_fp": "6839.88", "yes_ask": {"close_dollars": "0.2500", "high_dollars": "0.2500", "low_dollars": "0.2400", "open_dollars": "0.2500"}, "yes_bid": {"close_dollars": "0.2300", "high_dollars": "0.2300", "low_dollars": "0.2300", "open_dollars": "0.2300"}}, {"end_period_ts": 1780765200, "open_interest_fp": "75320.01", "price": {"close_dollars": "0.2400", "high_dollars": "0.2500", "low_dollars": "0.2300", "mean_dollars": "0.2341", "open_dollars": "0.2500", "previous_dollars": "0.2500"}, "volume_fp": "10139.64", "yes_ask": {"close_dollars": "0.2400", "high_dollars": "0.2500", "low_dollars": "0.2400", "open_dollars": "0.2500"}, "yes_bid": {"close_dollars": "0.2300", "high_dollars": "0.2400", "low_dollars": "0.2300", "open_dollars": "0.2300"}}, {"end_period_ts": 1780768800, "open_interest_fp": "78187.12", "price": {"close_dollars": "0.2400", "high_dollars": "0.2400", "low_dollars": "0.2300", "mean_dollars": "0.2379", "open_dollars": "0.2400", "previous_dollars": "0.2400"}, "volume_fp": "4475.33", "yes_ask": {"close_dollars": "0.2400", "high_dollars": "0.2400", "low_dollars": "0.2400", "open_dollars": "0.2400"}, "yes_bid": {"close_dollars": "0.2300", "high_dollars": "0.2300", "low_dollars": "0.2300", "open_dollars": "0.2300"}}, {"end_period_ts": 1780772400, "open_interest_fp": "82252.43", "price": {"close_dollars": "0.2400", "high_dollars": "0.2400", "low_dollars": "0.2300", "mean_dollars": "0.2397", "open_dollars": "0.2400", "previous_dollars": "0.2400"}, "volume_fp": "4293.33", "yes_ask": {"close_dollars": "0.2400", "high_dollars": "0.2400", "low_dollars": "0.2400", "open_dollars": "0.2400"}, "yes_bid": {"close_dollars": "0.2300", "high_dollars": "0.2300", "low_dollars": "0.2300", "open_dollars": "0.2300"}}, {"end_period_ts": 1780776000, "open_interest_fp": "85912.22", "price": {"close_dollars": "0.2400", "high_dollars": "0.2400", "low_dollars": "0.2300", "mean_dollars": "0.2388", "open_dollars": "0.2400", "previous_dollars": "0.2400"}, "volume_fp": "4865.85", "yes_ask": {"close_dollars": "0.2400", "high_dollars": "0.2400", "low_dollars": "0.2400", "open_dollars": "0.2400"}, "yes_bid": {"close_dollars": "0.2300", "high_dollars": "0.2300", "low_dollars": "0.2300", "open_dollars": "0.2300"}}, {"end_period_ts": 1780779600, "open_interest_fp": "100606.93", "price": {"close_dollars": "0.2400", "high_dollars": "0.2400", "low_dollars": "0.2300", "mean_dollars": "0.2388", "open_dollars": "0.2400", "previous_dollars": "0.2400"}, "volume_fp": "19200.05", "yes_ask": {"close_dollars": "0.2400", "high_dollars": "0.2400", "low_dollars": "0.2400", "open_dollars": "0.2400"}, "yes_bid": {"close_dollars": "0.2300", "high_dollars": "0.2300", "low_dollars": "0.2300", "open_dollars": "0.2300"}}, {"end_period_ts": 1780783200, "open_interest_fp": "119121.93", "price": {"close_dollars": "0.2400", "high_dollars": "0.2400", "low_dollars": "0.2300", "mean_dollars": "0.2396", "open_dollars": "0.2400", "previous_dollars": "0.2400"}, "volume_fp": "20327.00", "yes_ask": {"close_dollars": "0.2400", "high_dollars": "0.2400", "low_dollars": "0.2400", "open_dollars": "0.2400"}, "yes_bid": {"close_dollars": "0.2300", "high_dollars": "0.2300", "low_dollars": "0.2300", "open_dollars": "0.2300"}}, {"end_period_ts": 1780786800, "open_interest_fp": "147749.65", "price": {"close_dollars": "0.2500", "high_dollars": "0.2500", "low_dollars": "0.2300", "mean_dollars": "0.2400", "open_dollars": "0.2400", "previous_dollars": "0.2400"}, "volume_fp": "29238.40", "yes_ask": {"close_dollars": "0.2500", "high_dollars": "0.2500", "low_dollars": "0.2400", "open_dollars": "0.2400"}, "yes_bid": {"close_dollars": "0.2400", "high_dollars": "0.2400", "low_dollars": "0.2300", "open_dollars": "0.2300"}}, {"end_period_ts": 1780790400, "open_interest_fp": "190192.06", "price": {"close_dollars": "0.2500", "high_dollars": "0.2500", "low_dollars": "0.2400", "mean_dollars": "0.2500", "open_dollars": "0.2500", "previous_dollars": "0.2500"}, "volume_fp": "43150.86", "yes_ask": {"close_dollars": "0.2500", "high_dollars": "0.2500", "low_dollars": "0.2500", "open_dollars": "0.2500"}, "yes_bid": {"close_dollars": "0.2400", "high_dollars": "0.2400", "low_dollars": "0.2400", "open_dollars": "0.2400"}}, {"end_period_ts": 1780794000, "open_interest_fp": "223817.80", "price": {"close_dollars": "0.2500", "high_dollars": "0.2500", "low_dollars": "0.2400", "mean_dollars": "0.2499", "open_dollars": "0.2500", "previous_dollars": "0.2500"}, "volume_fp": "34346.90", "yes_ask": {"close_dollars": "0.2500", "high_dollars": "0.2500", "low_dollars": "0.2500", "open_dollars": "0.2500"}, "yes_bid": {"close_dollars": "0.2400", "high_dollars": "0.2400", "low_dollars": "0.2400", "open_dollars": "0.2400"}}, {"end_period_ts": 1780797600, "open_interest_fp": "402060.78", "price": {"close_dollars": "0.2400", "high_dollars": "0.2500", "low_dollars": "0.2400", "mean_dollars": "0.2492", "open_dollars": "0.2500", "previous_dollars": "0.2500"}, "volume_fp": "188332.05", "yes_ask": {"close_dollars": "0.2400", "high_dollars": "0.2500", "low_dollars": "0.2400", "open_dollars": "0.2500"}, "yes_bid": {"close_dollars": "0.2300", "high_dollars": "0.2400", "low_dollars": "0.2300", "open_dollars": "0.2400"}}], "ticker": "KXMLBGAME-26JUN062210LAALAD-LAA"}